README.md
setup.py
sunnydayk/__init__.py
sunnydayk/sunnydayk.py
sunnydayk.egg-info/PKG-INFO
sunnydayk.egg-info/SOURCES.txt
sunnydayk.egg-info/dependency_links.txt
sunnydayk.egg-info/requires.txt
sunnydayk.egg-info/top_level.txt