Metadata-Version: 2.1
Name: sunnydayk
Version: 2.0.0
Summary: Weather forecast data
Home-page: https://example.com
Author: yoshi
Author-email: your.email@example.com
License: MIT
Keywords: weather,forecast,openweather
Classifier: Development Status :: 3 - Alpha
Classifier: Intended Audience :: Developers
Classifier: Topic :: Software Development :: Build Tools
Classifier: License :: OSI Approved :: MIT License
Classifier: Programming Language :: Python :: 3.5
Classifier: Programming Language :: Python :: 3.6
Classifier: Programming Language :: Python :: 3.7
Classifier: Programming Language :: Python :: 3.8
